funvip/FunVIP_GUI.py
funvip/__init__.py
funvip/main.py
funvip/data/Option_manager.xlsx
funvip/data/__init__.py
funvip/data/genus_line.txt
funvip/external/MAFFT_LICENSE
funvip/external/MAFFT_Windows.zip
funvip/external/__init__.py
funvip/external/BLAST_Windows/Uninstall-ncbi-blast-2.12.0+.exe
funvip/external/BLAST_Windows/bin/blastn.exe
funvip/external/BLAST_Windows/bin/cleanup-blastdb-volumes.py
funvip/external/BLAST_Windows/bin/get_species_taxids.sh
funvip/external/BLAST_Windows/bin/legacy_blast.pl
funvip/external/BLAST_Windows/bin/makeblastdb.exe
funvip/external/BLAST_Windows/bin/nghttp2.dll
funvip/external/BLAST_Windows/bin/update_blastdb.pl
funvip/external/BLAST_Windows/doc/README.txt
funvip/external/FastTree_Windows/FastTree.exe
funvip/external/Gblocks_Windows_0.91b/Gblocks_0.91b/Gblocks.exe
funvip/external/Gblocks_Windows_0.91b/Gblocks_0.91b/nad3.pir
funvip/external/Gblocks_Windows_0.91b/Gblocks_0.91b/paths
funvip/external/Gblocks_Windows_0.91b/Gblocks_0.91b/Documentation/Gblocks_documentation.html
funvip/external/Gblocks_Windows_0.91b/Gblocks_0.91b/more_alignments/cox2.pir
funvip/external/Gblocks_Windows_0.91b/Gblocks_0.91b/more_alignments/cytb.pir
funvip/external/Gblocks_Windows_0.91b/Gblocks_0.91b/more_alignments/nad3.pir
funvip/external/Gblocks_Windows_0.91b/Gblocks_0.91b/more_alignments/nad5.pir
funvip/external/RAxML_Windows/GPL-3.0.txt
funvip/external/RAxML_Windows/README
funvip/external/RAxML_Windows/raxmlHPC-PTHREADS-AVX2.exe
funvip/external/iqtree/example.cf
funvip/external/iqtree/example.nex
funvip/external/iqtree/example.phy
funvip/external/iqtree/models.nex
funvip/external/iqtree/bin/iqtree2-click.exe
funvip/external/iqtree/bin/iqtree2.exe
funvip/external/iqtree/bin/libiomp5md.dll
funvip/external/mmseqs_Windows/LICENSE.md
funvip/external/mmseqs_Windows/README.md
funvip/external/mmseqs_Windows/mmseqs.bat
funvip/external/mmseqs_Windows/bin/busybox.exe
funvip/external/mmseqs_Windows/bin/cygbz2-1.dll
funvip-0.5.6.dist-info/licenses/LICENSE
funvip-0.5.6.dist-info/METADATA
funvip-0.5.6.dist-info/WHEEL
funvip-0.5.6.dist-info/entry_points.txt
funvip-0.5.6.dist-info/top_level.txt
funvip-0.5.6.dist-info/RECORD