Metadata-Version: 2.4
Name: FunVIP
Version: 0.5.6
Summary: Fungal Validation & Identification Pipeline
Author-email: Changwan Seo <wan101010@snu.ac.kr>
License: GPL-3.0
Project-URL: Homepage, https://github.com/Changwanseo/FunVIP
Requires-Python: <3.13,>=3.9
License-File: LICENSE
Requires-Dist: biopython==1.84
Requires-Dist: ete3==3.1.3
Requires-Dist: Cython
Requires-Dist: contourpy<1.3
Requires-Dist: dendropy
Requires-Dist: GenMine<1.5.0,>=1.3.0
Requires-Dist: lxml
Requires-Dist: matplotlib
Requires-Dist: numpy<2.0.0
Requires-Dist: openpyxl==3.1.0
Requires-Dist: pandas==2.2.2
Requires-Dist: psutil
Requires-Dist: pyyaml
Requires-Dist: sip>=4.19.4
Requires-Dist: scikit-learn
Requires-Dist: scipy
Requires-Dist: tabulate
Requires-Dist: unidecode==1.2.0
Requires-Dist: xlrd==2.0.1
Requires-Dist: xlsxwriter
Requires-Dist: xmltodict==0.12.0
Requires-Dist: PyQt5>=5.15.0; sys_platform != "darwin"
Dynamic: license-file
